indexdigest/__init__.py
indexdigest/database.py
indexdigest/schema.py
indexdigest/utils.py
indexdigest/cli/__init__.py
indexdigest/cli/add_linter.py
indexdigest/cli/script.py
indexdigest/formatters/__init__.py
indexdigest/formatters/plain.py
indexdigest/formatters/syslog.py
indexdigest/formatters/yaml.py
indexdigest/linters/__init__.py
indexdigest/linters/linter_0002_not_used_indices.py
indexdigest/linters/linter_0004_redundant_indices.py
indexdigest/linters/linter_0006_not_used_columns_and_tables.py
indexdigest/linters/linter_0019_queries_not_using_indices.py
indexdigest/linters/linter_0020_filesort_temporary_table.py
indexdigest/linters/linter_0026_full_table_scan.py
indexdigest/linters/linter_0027_selects_with_like.py
indexdigest/linters/linter_0028_data_not_updated_recently.py
indexdigest/linters/linter_0028_data_too_old.py
indexdigest/linters/linter_0031_low_cardinality_index.py
indexdigest/linters/linter_0032_utf_latin_columns.py
indexdigest/linters/linter_0034_missing_primary_index.py
indexdigest/linters/linter_0036_use_innodb.py
indexdigest/linters/linter_0070_insert_ignore.py
indexdigest/linters/linter_0074_single_column.py
indexdigest/linters/linter_0075_test_tables.py
indexdigest/linters/linter_0089_empty_tables.py
indexdigest/linters/linter_0092_select_star.py
indexdigest/linters/linter_0093_having_clause.py
indexdigest/linters/linter_0094_generic_primary_key.py
indexdigest/linters/linter_0118_high_offset_selects.py
indexdigest/linters/linter_0164_empty_database.py
indexdigest/test/__init__.py
indexdigest/test/test_0004_redundant_indices_core.py
indexdigest/test/test_0089_handle_sql_errors.py
indexdigest/test/test_0107_schema_partitions.py
indexdigest/test/test_schema.py
indexdigest/test/cli/__init__.py
indexdigest/test/cli/test_script.py
indexdigest/test/core/__init__.py
indexdigest/test/core/test_columns.py
indexdigest/test/core/test_database.py
indexdigest/test/core/test_indices.py
indexdigest/test/core/test_query.py
indexdigest-1.7.0.dist-info/licenses/LICENSE
indexdigest-1.7.0.dist-info/METADATA
indexdigest-1.7.0.dist-info/WHEEL
indexdigest-1.7.0.dist-info/entry_points.txt
indexdigest-1.7.0.dist-info/top_level.txt
indexdigest-1.7.0.dist-info/RECORD
