Metadata-Version: 2.4
Name: indexdigest
Version: 1.7.0
Summary: Analyses your database queries and schema and suggests indices and schema improvements
Home-page: https://github.com/macbre/index-digest
Author: Maciej Brencz
Author-email: maciej.brencz@gmail.com
License: MIT
Classifier: Development Status :: 5 - Production/Stable
Classifier: Intended Audience :: Developers
Classifier: Intended Audience :: System Administrators
Classifier: Topic :: Database
Classifier: License :: OSI Approved :: MIT License
Classifier: Programming Language :: Python :: 3
Classifier: Programming Language :: Python :: 3.8
Classifier: Programming Language :: Python :: 3.9
Classifier: Programming Language :: Python :: 3.10
Requires-Python: >=3.9
License-File: LICENSE
Requires-Dist: docopt==0.6.2
Requires-Dist: PyYAML==6.0.2
Requires-Dist: mysqlclient==2.2.7
Requires-Dist: sql_metadata==2.17.0
Requires-Dist: termcolor==3.1.0
Requires-Dist: yamlordereddictloader==0.4.2
Provides-Extra: dev
Requires-Dist: coverage==7.8.1; extra == "dev"
Requires-Dist: pylint==3.3.7; extra == "dev"
Requires-Dist: pytest==8.3.5; extra == "dev"
Requires-Dist: pytest-cov==6.1.1; extra == "dev"
Requires-Dist: twine==6.1.0; extra == "dev"
Dynamic: author
Dynamic: author-email
Dynamic: classifier
Dynamic: description
Dynamic: description-content-type
Dynamic: home-page
Dynamic: license
Dynamic: license-file
Dynamic: provides-extra
Dynamic: requires-dist
Dynamic: requires-python
Dynamic: summary
